invenio_sword/__init__.py
invenio_sword/api.py
invenio_sword/config.py
invenio_sword/enum.py
invenio_sword/ext.py
invenio_sword/permissions.py
invenio_sword/schemas.py
invenio_sword/serializers.py
invenio_sword/tasks.py
invenio_sword/typing.py
invenio_sword/utils.py
invenio_sword/version.py
invenio_sword/metadata/__init__.py
invenio_sword/metadata/base.py
invenio_sword/metadata/sword.py
invenio_sword/packaging/__init__.py
invenio_sword/packaging/bagit.py
invenio_sword/packaging/base.py
invenio_sword/packaging/binary.py
invenio_sword/packaging/zip.py
invenio_sword/views/__init__.py
invenio_sword/views/base.py
invenio_sword/views/blueprint.py
invenio_sword/views/file.py
invenio_sword/views/fileset.py
invenio_sword/views/metadata.py
invenio_sword/views/service_document.py
invenio_sword/views/staging.py
invenio_sword/views/status.py
invenio_sword-1.0.0a10.dist-info/METADATA
invenio_sword-1.0.0a10.dist-info/WHEEL
invenio_sword-1.0.0a10.dist-info/entry_points.txt
invenio_sword-1.0.0a10.dist-info/top_level.txt
invenio_sword-1.0.0a10.dist-info/RECORD
